LICENSE.md
financial_entity_cleaner/__init__.py
financial_entity_cleaner/__main__.py
financial_entity_cleaner/batch/__init__.py
financial_entity_cleaner/batch/cleaner.py
financial_entity_cleaner/country/__init__.py
financial_entity_cleaner/country/exceptions.py
financial_entity_cleaner/country/iso3166.py
financial_entity_cleaner/country/search_country.py
financial_entity_cleaner/id/__init__.py
financial_entity_cleaner/id/banking.py
financial_entity_cleaner/id/exceptions.py
financial_entity_cleaner/text/__init__.py
financial_entity_cleaner/text/cleaning_rules.py
financial_entity_cleaner/text/exceptions.py
financial_entity_cleaner/text/legal_forms/ar_legal_forms.json
financial_entity_cleaner/text/legal_forms/at_legal_forms.json
financial_entity_cleaner/text/legal_forms/au_legal_forms.json
financial_entity_cleaner/text/legal_forms/available_legal_forms.json
financial_entity_cleaner/text/legal_forms/br_legal_forms.json
financial_entity_cleaner/text/legal_forms/ca_legal_forms.json
financial_entity_cleaner/text/legal_forms/de_legal_forms.json
financial_entity_cleaner/text/legal_forms/es_legal_forms.json
financial_entity_cleaner/text/legal_forms/fr_legal_forms.json
financial_entity_cleaner/text/legal_forms/gb_legal_forms.json
financial_entity_cleaner/text/legal_forms/id_legal_forms.json
financial_entity_cleaner/text/legal_forms/in_legal_forms.json
financial_entity_cleaner/text/legal_forms/it_legal_forms.json
financial_entity_cleaner/text/legal_forms/nl_legal_forms.json
financial_entity_cleaner/text/legal_forms/nz_legal_forms.json
financial_entity_cleaner/text/legal_forms/pt_legal_forms.json
financial_entity_cleaner/text/legal_forms/sg_legal_forms.json
financial_entity_cleaner/text/legal_forms/us_legal_forms.json
financial_entity_cleaner/text/name.py
financial_entity_cleaner/utils/__init__.py
financial_entity_cleaner/utils/error_handler.py
financial_entity_cleaner/utils/lib.py
financial_entity_cleaner/utils/logger.conf
financial_entity_cleaner/utils/simple_cleaner.py
financial_entity_cleaner-0.2.0.dist-info/entry_points.txt
financial_entity_cleaner-0.2.0.dist-info/LICENSE.md
financial_entity_cleaner-0.2.0.dist-info/WHEEL
financial_entity_cleaner-0.2.0.dist-info/METADATA
financial_entity_cleaner-0.2.0.dist-info/RECORD
