Metadata-Version: 2.1
Name: financial-entity-cleaner
Version: 0.2.0
Summary: Normalization of data for entity matching
Home-page: https://github.com/os-climate/financial-entity-cleaner
License: Apache 2
Keywords: cleaner,validator,data normalizer
Author: Os-Climate Foundation
Author-email: test_os-climate@gmail.com
Requires-Python: >=3.6.2,<3.11
Classifier: Development Status :: 5 - Production/Stable
Classifier: Intended Audience :: Developers
Classifier: License :: OSI Approved :: Apache Software License
Classifier: License :: Other/Proprietary License
Classifier: Operating System :: MacOS
Classifier: Operating System :: Microsoft :: Windows
Classifier: Operating System :: POSIX :: Linux
Classifier: Programming Language :: Python :: 3
Classifier: Programming Language :: Python :: 3.10
Classifier: Programming Language :: Python :: 3.7
Classifier: Programming Language :: Python :: 3.8
Classifier: Programming Language :: Python :: 3.9
Requires-Dist: hdx-python-country (==3.0.7)
Requires-Dist: hdx-python-utilities (==3.0.7)
Requires-Dist: numpy (>=1.16.0)
Requires-Dist: pandas (>=1.1.5)
Requires-Dist: python-stdnum (==1.17)
Requires-Dist: tqdm (>=4.62.2)
